emailutil/__init__.py
emailutil/emailutil.py
atd_email_util-0.0.2.dist-info/LICENSE
atd_email_util-0.0.2.dist-info/METADATA
atd_email_util-0.0.2.dist-info/WHEEL
atd_email_util-0.0.2.dist-info/top_level.txt
atd_email_util-0.0.2.dist-info/RECORD
